lotd/__init__.py
lotd/collators.py
lotd/dataset_builders.py
lotd/filters.py
lotd/processors.py
lotd/templates.py
lotd/utils.py
lotd-0.1.4.dist-info/licenses/LICENSE
lotd-0.1.4.dist-info/METADATA
lotd-0.1.4.dist-info/WHEEL
lotd-0.1.4.dist-info/top_level.txt
lotd-0.1.4.dist-info/RECORD
